jinja2_git_dir/__init__.py
jinja2_git_dir/py.typed
jinja2_git_dir-0.4.1.dist-info/METADATA
jinja2_git_dir-0.4.1.dist-info/WHEEL
jinja2_git_dir-0.4.1.dist-info/licenses/LICENSE
jinja2_git_dir-0.4.1.dist-info/RECORD
