Metadata-Version: 2.4
Name: jinja2-git-dir
Version: 0.4.1
Summary: Jinja2 filter extension for detecting if a directory is a git repository
Project-URL: repository, https://github.com/gordon-code/jinja2-git-dir/
Author-email: Will Gordon <will@gordoncode.dev>
License: MIT License
License-File: LICENSE
Keywords: copier,extension,filters,jinja,jinja2
Classifier: Development Status :: 5 - Production/Stable
Classifier: Intended Audience :: Developers
Classifier: License :: OSI Approved :: MIT License
Classifier: Operating System :: OS Independent
Classifier: Programming Language :: Python :: 3
Classifier: Typing :: Typed
Requires-Python: >=3.9
Requires-Dist: jinja2>=3.0
